COPYING
README
setup.py
Machina.egg-info/PKG-INFO
Machina.egg-info/SOURCES.txt
Machina.egg-info/dependency_links.txt
Machina.egg-info/top_level.txt
machina/__init__.py
machina/machina.py
scripts/machina