Metadata-Version: 1.0
Name: Machina
Version: 0.1
Summary: This package provides a simple, lightweight but very effective and extremely extensible building framework designed in the spirit of Make, Ant and Rake.
Home-page: http://code.google.com/p/machina-pythonica
Author: Petko D. (pdp) Petkov
Author-email: pdp@gnucitizen.org
License: UNKNOWN
Platform: UNKNOWN
